bonos/__init__.py
bonos/analizar_spread.py
bonos/flujos.py
bonos/optimizacion.py
bonos/riesgo.py
bonos/sensibilidad.py
bonos/simulacion.py
bonos/simular_rebalanceo.py
bonos/tasas.py
bonos/valuacion.py
bonos/visualizacion.py
pybono-1.1.8.dist-info/LICENSE
pybono-1.1.8.dist-info/METADATA
pybono-1.1.8.dist-info/WHEEL
pybono-1.1.8.dist-info/top_level.txt
pybono-1.1.8.dist-info/RECORD
