Metadata-Version: 2.1
Name: pybono
Version: 1.1.8
Summary: Librería para análisis y cálculos de bonos financieros
Home-page: https://github.com/LuisHCalderon/pybono
Author: Luis Humberto Calderon Baldeón
Author-email: luis.calderon.b@uni.pe
License: MIT
Keywords: bond financial analysis yield to maturity duration convexity
Requires-Python: >=3.7
License-File: LICENSE
Requires-Dist: numpy>=1.21.0
Requires-Dist: pandas>=2.2.2
Requires-Dist: matplotlib>=3.5.0
